html/gdr.html
html/gdr.odt
html/gdrBuilder.html
html/gdrBuilder.odt
html/gdrOperator.html
html/gdrOperator.odt
html/opcua.html
html/opcua.odt
stdcom/__init__.py
stdcom/frontend.py
stdcom/frontend.ui
stdcom/frontendOPCUA.py
stdcom/gdr.py
stdcom/gdr.ui
stdcom/gdrGeneric.py
stdcom/ipportdialog.py
stdcom/ipportdialog.ui
stdcom/operatorGDRWindow.py
stdcom/operatorGDRWindow.ui
stdcom/operatorGDRWindowGeneric.py
stdcom/pjanice.py
stdcom/pjanice.ui
stdcom/pjaniceGeneric.py
stdcom/pjanicesimple.py
stdcom/pjanicesimple.ui
stdcom/pjanicesimpleGeneric.py
stdcom/postgresConfig.py
stdcom/postgresConfig.ui
stdcom/stdcom.py
stdcom/stdcomqt5.py
stdcom/stdcomqt5treeewidget.py
stdcom/stdcomqt5treeewidget.ui
stdcom/stdcomqt5widget.py
stdcom/stdpostgresdialog.py
stdcom/stdpostgresdialog.ui
stdcom/stdsql.py
stdcom/stdsqlgdr.py
stdcom/stec-config.ui
stdcom/stec-configure.py
stdcom/stec-gdr
stdcom/stec-opcua
stdcom/stec-pjanice
stdcom/__pycache__/__init__.cpython-310.pyc
stdcom/__pycache__/frontend.cpython-310.pyc
stdcom/__pycache__/frontendOPCUA.cpython-310.pyc
stdcom/__pycache__/gdr.cpython-310.pyc
stdcom/__pycache__/gdrGeneric.cpython-310.pyc
stdcom/__pycache__/ipportdialog.cpython-310.pyc
stdcom/__pycache__/operatorGDRWindow.cpython-310.pyc
stdcom/__pycache__/operatorGDRWindowGeneric.cpython-310.pyc
stdcom/__pycache__/pjanice.cpython-310.pyc
stdcom/__pycache__/pjaniceGeneric.cpython-310.pyc
stdcom/__pycache__/pjanicesimple.cpython-310.pyc
stdcom/__pycache__/pjanicesimpleGeneric.cpython-310.pyc
stdcom/__pycache__/postgresConfig.cpython-310.pyc
stdcom/__pycache__/stdcom.cpython-310.pyc
stdcom/__pycache__/stdcomqt5.cpython-310.pyc
stdcom/__pycache__/stdcomqt5treeewidget.cpython-310.pyc
stdcom/__pycache__/stdcomqt5widget.cpython-310.pyc
stdcom/__pycache__/stdpostgresdialog.cpython-310.pyc
stdcom/__pycache__/stdsql.cpython-310.pyc
stdcom/__pycache__/stdsqlgdr.cpython-310.pyc
stdcom/examples/ipconfig.py
stdcom/examples/stdcomqt5qtree.py
stdcom/examples/stec-gdr
stdcom/examples/stec-opcua
stdcom-1.8.1.dist-info/LICENSE.txt
stdcom-1.8.1.dist-info/METADATA
stdcom-1.8.1.dist-info/WHEEL
stdcom-1.8.1.dist-info/top_level.txt
stdcom-1.8.1.dist-info/RECORD
